acc_lib/__init__.py
acc_lib/acc_lib.py
acc_lib-0.0.29.dist-info/LICENSE
acc_lib-0.0.29.dist-info/METADATA
acc_lib-0.0.29.dist-info/WHEEL
acc_lib-0.0.29.dist-info/top_level.txt
acc_lib-0.0.29.dist-info/RECORD
