Metadata-Version: 2.1
Name: acc-lib
Version: 0.0.29
Summary: Personal collection of methods useful for accelerator physics
Home-page: 
Author: Elias Walter Waagaard
Author-email: elias.walter.waagaard@cern.ch
Classifier: Programming Language :: Python :: 3
Classifier: Operating System :: OS Independent
Requires-Python: ~=3.7
License-File: LICENSE
Requires-Dist: numpy
Requires-Dist: matplotlib
Requires-Dist: scipy
Requires-Dist: NAFFlib
Requires-Dist: pandas
Provides-Extra: all
Requires-Dist: numpy ; extra == 'all'
Requires-Dist: matplotlib ; extra == 'all'
Requires-Dist: scipy ; extra == 'all'
Requires-Dist: NAFFlib ; extra == 'all'
Requires-Dist: pandas ; extra == 'all'
Provides-Extra: core
Requires-Dist: numpy ; extra == 'core'
Requires-Dist: matplotlib ; extra == 'core'
Requires-Dist: scipy ; extra == 'core'
Requires-Dist: NAFFlib ; extra == 'core'
Requires-Dist: pandas ; extra == 'core'
Provides-Extra: dev
Provides-Extra: doc
Provides-Extra: test
